ordipool/__init__.py
ordipool/models/__init__.py
ordipool/models/transaction_info.py
ordipool/ordipool/__init__.py
ordipool/ordipool/mempoolio.py
ordipool/utils/__init__.py
ordipool/utils/utils.py
ordipool-1.2.0.dist-info/LICENSE
ordipool-1.2.0.dist-info/METADATA
ordipool-1.2.0.dist-info/WHEEL
ordipool-1.2.0.dist-info/top_level.txt
ordipool-1.2.0.dist-info/RECORD
