Metadata-Version: 2.1
Name: ordipool
Version: 1.2.0
Summary: A mempool sdk library tailored for multiple usecases including ordinals
Author: twosatsmaxi
License: Apache License
Project-URL: Homepage, https://github.com/twosatsmaxi/ordipool
Keywords: mempool,ordinals,sdk,library,bitmap
Classifier: Intended Audience :: Developers
Classifier: License :: OSI Approved :: MIT License
Classifier: Programming Language :: Python :: 3.10
Classifier: Programming Language :: Python :: 3.11
Classifier: Programming Language :: Python :: Implementation :: CPython
Classifier: Operating System :: OS Independent
Classifier: Topic :: Software Development :: Libraries :: Python Modules
Requires-Python: >=3.10
License-File: LICENSE
Requires-Dist: requests ~=2.31.0
